Metadata-Version: 2.3
Name: orca-python
Version: 0.13.0
Summary: Python SDK for the Predixus Orca product
Author: Frederick Mannings
Author-email: fred@orc-a.io
Requires-Python: >=3.10
Classifier: Programming Language :: Python :: 3
Classifier: Programming Language :: Python :: 3.10
Classifier: Programming Language :: Python :: 3.11
Classifier: Programming Language :: Python :: 3.12
Classifier: Programming Language :: Python :: 3.13
Requires-Dist: grpcio (>=1.71.0,<2.0.0)
Requires-Dist: grpcio-reflection (>=1.74.0,<2.0.0)
Requires-Dist: grpcio-tools (>=1.71.0,<2.0.0)
